<?xml version="1.0" encoding="UTF-8"?>
<metadata xml:lang="it"><Esri><CreaDate>20210402</CreaDate><CreaTime>13061200</CreaTime><ArcGISFormat>1.0</ArcGISFormat><SyncOnce>TRUE</SyncOnce><DataProperties><lineage><Process ToolSource="c:\program files (x86)\arcgis\desktop10.5\ArcToolbox\Toolboxes\Spatial Analyst Tools.tbx\ExtractValuesToPoints" Date="20210402" Time="130541">ExtractValuesToPoints 11_Top_L1 GALayerToGri7 C:\Users\Utente\Documents\ArcGIS\Default.gdb\Extract_shp6 NONE VALUE_ONLY</Process></lineage></DataProperties></Esri></metadata>
