<PAMDataset>
  <Metadata domain="Esri">
    <MDI key="PyramidResamplingType">AVERAGE</MDI>
  </Metadata>
  <PAMRasterBand band="1">
    <Histograms>
      <HistItem>
        <HistMin>96.58847808837891</HistMin>
        <HistMax>119.313606262207</HistMax>
        <BucketCount>256</BucketCount>
        <IncludeOutOfRange>1</IncludeOutOfRange>
        <Approximate>0</Approximate>
        <HistCounts>3|0|2|4|3|2|2|4|4|7|6|6|6|4|11|5|3|9|6|8|6|12|9|8|10|12|9|10|10|11|11|14|12|15|15|18|16|425|624|2078|3174|3481|2828|4273|4069|4591|3347|2828|2663|2822|3194|3672|3780|4547|4215|4666|4660|4877|4716|4735|5291|5042|4891|4855|5471|5682|5416|4751|5234|5678|6260|6756|6111|5506|5320|5450|5501|5767|6776|10782|7879|7014|7743|8858|11047|10731|9112|7070|5975|6149|6109|6263|6138|7060|6807|7464|10445|9979|10323|10286|11043|11648|10948|10342|9897|11977|15153|11815|9565|10130|10827|10067|9595|9212|9176|9817|9466|9162|9572|8704|9292|9954|11517|11306|9757|10053|10621|9903|8560|9165|9139|9321|9798|9327|9234|8750|7424|6932|7063|6872|6182|5477|5920|6799|6920|8401|7703|8563|9633|11590|10151|9242|9080|12993|12347|8106|6664|6036|5746|5598|4882|5242|5455|4779|5380|4540|4016|3935|4936|4344|3317|3654|4039|4646|3289|3636|4108|4931|4809|6160|5956|5114|5046|6704|7892|2345|1885|1650|1124|940|694|570|436|264|234|237|201|188|147|130|122|136|117|109|95|95|86|81|84|82|85|85|111|83|72|84|65|65|61|55|49|27|37|42|44|22|28|24|16|29|24|27|33|21|16|16|15|16|26|8|7|9|6|8|7|4|5|2|2|7|4|2|2|5|1|1</HistCounts>
      </HistItem>
    </Histograms>
    <Metadata>
      <MDI key="RepresentationType">ATHEMATIC</MDI>
      <MDI key="STATISTICS_COVARIANCES">10.9208075839162</MDI>
      <MDI key="STATISTICS_MAXIMUM">119.31360626221</MDI>
      <MDI key="STATISTICS_MEAN">106.91379372878</MDI>
      <MDI key="STATISTICS_MINIMUM">96.588478088379</MDI>
      <MDI key="STATISTICS_SKIPFACTORX">1</MDI>
      <MDI key="STATISTICS_SKIPFACTORY">1</MDI>
      <MDI key="STATISTICS_STDDEV">3.3046645191178</MDI>
    </Metadata>
  </PAMRasterBand>
</PAMDataset>
